{
  "date": "2026-07-17",
  "ticker": "THEQ",
  "prior_date": "2026-07-16",
  "diff": [
    {
      "ticker": "AAPL",
      "name": "APPLE INC COMMON STOCK USD.00001",
      "identifier": "037833100",
      "sector": "",
      "status": "unchanged",
      "quantity_today": 177.0,
      "quantity_prior": 177.0,
      "quantity_pct_change": 0.0,
      "pct_of_fund_today": 0.157825,
      "pct_of_fund_prior": 0.154772,
      "pct_of_fund_change": 0.0031,
      "market_value_today": 58987.02
    },
    {
      "ticker": "ABBV",
      "name": "ABBVIE INC COMMON STOCK USD.01",
      "identifier": "00287Y109",
      "sector": "",
      "status": "unchanged",
      "quantity_today": 27.0,
      "quantity_prior": 27.0,
      "quantity_pct_change": 0.0,
      "pct_of_fund_today": 0.018377,
      "pct_of_fund_prior": 0.017598,
      "pct_of_fund_change": 0.0008,
      "market_value_today": 6868.53
    },
    {
      "ticker": "ACN",
      "name": "ACCENTURE PLC CL A COMMON STOCK USD.0000225",
      "identifier": "G1151C101",
      "sector": "",
      "status": "unchanged",
      "quantity_today": 129.0,
      "quantity_prior": 129.0,
      "quantity_pct_change": 0.0,
      "pct_of_fund_today": 0.049912,
      "pct_of_fund_prior": 0.047193,
      "pct_of_fund_change": 0.0027,
      "market_value_today": 18654.69
    },
    {
      "ticker": "ADP",
      "name": "AUTOMATIC DATA PROCESSING COMMON STOCK USD.1",
      "identifier": "053015103",
      "sector": "",
      "status": "unchanged",
      "quantity_today": 97.0,
      "quantity_prior": 97.0,
      "quantity_pct_change": 0.0,
      "pct_of_fund_today": 0.066585,
      "pct_of_fund_prior": 0.064092,
      "pct_of_fund_change": 0.0025,
      "market_value_today": 24886.32
    },
    {
      "ticker": "AEE",
      "name": "AMEREN CORPORATION COMMON STOCK USD.01",
      "identifier": "023608102",
      "sector": "",
      "status": "unchanged",
      "quantity_today": 309.0,
      "quantity_prior": 309.0,
      "quantity_pct_change": 0.0,
      "pct_of_fund_today": 0.093506,
      "pct_of_fund_prior": 0.091891,
      "pct_of_fund_change": 0.0016,
      "market_value_today": 34947.9
    },
    {
      "ticker": "ALL",
      "name": "ALLSTATE CORP COMMON STOCK USD.01",
      "identifier": "020002101",
      "sector": "",
      "status": "unchanged",
      "quantity_today": 260.0,
      "quantity_prior": 260.0,
      "quantity_pct_change": 0.0,
      "pct_of_fund_today": 0.16825,
      "pct_of_fund_prior": 0.166245,
      "pct_of_fund_change": 0.002,
      "market_value_today": 62883.6
    },
    {
      "ticker": "AMAT",
      "name": "APPLIED MATERIALS INC COMMON STOCK USD.01",
      "identifier": "038222105",
      "sector": "",
      "status": "unchanged",
      "quantity_today": 20.0,
      "quantity_prior": 20.0,
      "quantity_pct_change": 0.0,
      "pct_of_fund_today": 0.030016,
      "pct_of_fund_prior": 0.030941,
      "pct_of_fund_change": -0.0009,
      "market_value_today": 11218.6
    },
    {
      "ticker": "AMD",
      "name": "ADVANCED MICRO DEVICES COMMON STOCK USD.01",
      "identifier": "007903107",
      "sector": "",
      "status": "unchanged",
      "quantity_today": 34.0,
      "quantity_prior": 34.0,
      "quantity_pct_change": 0.0,
      "pct_of_fund_today": 0.04557,
      "pct_of_fund_prior": 0.048035,
      "pct_of_fund_change": -0.0025,
      "market_value_today": 17031.96
    },
    {
      "ticker": "AME",
      "name": "AMETEK INC COMMON STOCK USD.01",
      "identifier": "031100100",
      "sector": "",
      "status": "unchanged",
      "quantity_today": 52.0,
      "quantity_prior": 52.0,
      "quantity_pct_change": 0.0,
      "pct_of_fund_today": 0.033016,
      "pct_of_fund_prior": 0.032422,
      "pct_of_fund_change": 0.0006,
      "market_value_today": 12339.6
    },
    {
      "ticker": "ANET",
      "name": "ARISTA NETWORKS INC COMMON STOCK USD.0001",
      "identifier": "040413205",
      "sector": "",
      "status": "unchanged",
      "quantity_today": 239.0,
      "quantity_prior": 239.0,
      "quantity_pct_change": 0.0,
      "pct_of_fund_today": 0.107788,
      "pct_of_fund_prior": 0.109706,
      "pct_of_fund_change": -0.0019,
      "market_value_today": 40285.84
    },
    {
      "ticker": "APH",
      "name": "AMPHENOL CORP CL A COMMON STOCK USD.001",
      "identifier": "032095101",
      "sector": "",
      "status": "unchanged",
      "quantity_today": 407.0,
      "quantity_prior": 407.0,
      "quantity_pct_change": 0.0,
      "pct_of_fund_today": 0.166764,
      "pct_of_fund_prior": 0.170652,
      "pct_of_fund_change": -0.0039,
      "market_value_today": 62327.98
    },
    {
      "ticker": "APP",
      "name": "APPLOVIN CORP CLASS A COMMON STOCK USD.00003",
      "identifier": "03831W108",
      "sector": "",
      "status": "unchanged",
      "quantity_today": 48.0,
      "quantity_prior": 48.0,
      "quantity_pct_change": 0.0,
      "pct_of_fund_today": 0.055799,
      "pct_of_fund_prior": 0.058021,
      "pct_of_fund_change": -0.0022,
      "market_value_today": 20855.04
    },
    {
      "ticker": "ATO",
      "name": "ATMOS ENERGY CORP COMMON STOCK",
      "identifier": "049560105",
      "sector": "",
      "status": "unchanged",
      "quantity_today": 104.0,
      "quantity_prior": 104.0,
      "quantity_pct_change": 0.0,
      "pct_of_fund_today": 0.049542,
      "pct_of_fund_prior": 0.048588,
      "pct_of_fund_change": 0.001,
      "market_value_today": 18516.16
    },
    {
      "ticker": "AVGO",
      "name": "BROADCOM INC COMMON STOCK",
      "identifier": "11135F101",
      "sector": "",
      "status": "unchanged",
      "quantity_today": 78.0,
      "quantity_prior": 78.0,
      "quantity_pct_change": 0.0,
      "pct_of_fund_today": 0.078146,
      "pct_of_fund_prior": 0.082112,
      "pct_of_fund_change": -0.004,
      "market_value_today": 29207.1
    },
    {
      "ticker": "AZO",
      "name": "AUTOZONE INC COMMON STOCK USD.01",
      "identifier": "053332102",
      "sector": "",
      "status": "unchanged",
      "quantity_today": 6.0,
      "quantity_prior": 6.0,
      "quantity_pct_change": 0.0,
      "pct_of_fund_today": 0.049158,
      "pct_of_fund_prior": 0.047588,
      "pct_of_fund_change": 0.0016,
      "market_value_today": 18372.96
    },
    {
      "ticker": "BKNG",
      "name": "BOOKING HOLDINGS INC COMMON STOCK USD.008",
      "identifier": "09857L108",
      "sector": "",
      "status": "unchanged",
      "quantity_today": 20.0,
      "quantity_prior": 20.0,
      "quantity_pct_change": 0.0,
      "pct_of_fund_today": 0.009879,
      "pct_of_fund_prior": 0.009761,
      "pct_of_fund_change": 0.0001,
      "market_value_today": 3692.2
    },
    {
      "ticker": "BRK.B",
      "name": "BERKSHIRE HATHAWAY INC CL B COMMON STOCK USD.0033",
      "identifier": "084670702",
      "sector": "",
      "status": "unchanged",
      "quantity_today": 65.0,
      "quantity_prior": 65.0,
      "quantity_pct_change": 0.0,
      "pct_of_fund_today": 0.08576,
      "pct_of_fund_prior": 0.084752,
      "pct_of_fund_change": 0.001,
      "market_value_today": 32052.8
    },
    {
      "ticker": "BSX",
      "name": "BOSTON SCIENTIFIC CORP COMMON STOCK USD.01",
      "identifier": "101137107",
      "sector": "",
      "status": "unchanged",
      "quantity_today": 316.0,
      "quantity_prior": 316.0,
      "quantity_pct_change": 0.0,
      "pct_of_fund_today": 0.037726,
      "pct_of_fund_prior": 0.036313,
      "pct_of_fund_change": 0.0014,
      "market_value_today": 14099.92
    },
    {
      "ticker": "CAH",
      "name": "CARDINAL HEALTH INC COMMON STOCK",
      "identifier": "14149Y108",
      "sector": "",
      "status": "unchanged",
      "quantity_today": 66.0,
      "quantity_prior": 66.0,
      "quantity_pct_change": 0.0,
      "pct_of_fund_today": 0.040389,
      "pct_of_fund_prior": 0.039639,
      "pct_of_fund_change": 0.0008,
      "market_value_today": 15095.52
    },
    {
      "ticker": "CB",
      "name": "CHUBB LTD COMMON STOCK",
      "identifier": "H1467J104",
      "sector": "",
      "status": "unchanged",
      "quantity_today": 279.0,
      "quantity_prior": 279.0,
      "quantity_pct_change": 0.0,
      "pct_of_fund_today": 0.256568,
      "pct_of_fund_prior": 0.251367,
      "pct_of_fund_change": 0.0052,
      "market_value_today": 95892.3
    },
    {
      "ticker": "CBOE",
      "name": "CBOE GLOBAL MARKETS INC COMMON STOCK",
      "identifier": "12503M108",
      "sector": "",
      "status": "unchanged",
      "quantity_today": 165.0,
      "quantity_prior": 165.0,
      "quantity_pct_change": 0.0,
      "pct_of_fund_today": 0.122681,
      "pct_of_fund_prior": 0.12208,
      "pct_of_fund_change": 0.0006,
      "market_value_today": 45851.85
    },
    {
      "ticker": "CDNS",
      "name": "CADENCE DESIGN SYS INC COMMON STOCK USD.01",
      "identifier": "127387108",
      "sector": "",
      "status": "unchanged",
      "quantity_today": 109.0,
      "quantity_prior": 109.0,
      "quantity_pct_change": 0.0,
      "pct_of_fund_today": 0.106346,
      "pct_of_fund_prior": 0.108117,
      "pct_of_fund_change": -0.0018,
      "market_value_today": 39746.85
    },
    {
      "ticker": "CHKP",
      "name": "CHECK POINT SOFTWARE TECH COMMON STOCK USD.01",
      "identifier": "M22465104",
      "sector": "",
      "status": "unchanged",
      "quantity_today": 136.0,
      "quantity_prior": 136.0,
      "quantity_pct_change": 0.0,
      "pct_of_fund_today": 0.049673,
      "pct_of_fund_prior": 0.048073,
      "pct_of_fund_change": 0.0016,
      "market_value_today": 18565.36
    },
    {
      "ticker": "CIEN",
      "name": "CIENA CORP COMMON STOCK USD.01",
      "identifier": "171779309",
      "sector": "",
      "status": "unchanged",
      "quantity_today": 48.0,
      "quantity_prior": 48.0,
      "quantity_pct_change": 0.0,
      "pct_of_fund_today": 0.049934,
      "pct_of_fund_prior": 0.053629,
      "pct_of_fund_change": -0.0037,
      "market_value_today": 18662.88
    },
    {
      "ticker": "CL",
      "name": "COLGATE PALMOLIVE CO COMMON STOCK USD1.0",
      "identifier": "194162103",
      "sector": "",
      "status": "unchanged",
      "quantity_today": 851.0,
      "quantity_prior": 851.0,
      "quantity_pct_change": 0.0,
      "pct_of_fund_today": 0.21419,
      "pct_of_fund_prior": 0.207833,
      "pct_of_fund_change": 0.0064,
      "market_value_today": 80053.57
    },
    {
      "ticker": "CME",
      "name": "CME GROUP INC COMMON STOCK USD.01",
      "identifier": "12572Q105",
      "sector": "",
      "status": "unchanged",
      "quantity_today": 132.0,
      "quantity_prior": 132.0,
      "quantity_pct_change": 0.0,
      "pct_of_fund_today": 0.086977,
      "pct_of_fund_prior": 0.08641,
      "pct_of_fund_change": 0.0006,
      "market_value_today": 32507.64
    },
    {
      "ticker": "CMS",
      "name": "CMS ENERGY CORP COMMON STOCK USD.01",
      "identifier": "125896100",
      "sector": "",
      "status": "unchanged",
      "quantity_today": 564.0,
      "quantity_prior": 564.0,
      "quantity_pct_change": 0.0,
      "pct_of_fund_today": 0.112257,
      "pct_of_fund_prior": 0.111464,
      "pct_of_fund_change": 0.0008,
      "market_value_today": 41955.96
    },
    {
      "ticker": "COR",
      "name": "CENCORA INC COMMON STOCK USD.01",
      "identifier": "03073E105",
      "sector": "",
      "status": "unchanged",
      "quantity_today": 211.0,
      "quantity_prior": 211.0,
      "quantity_pct_change": 0.0,
      "pct_of_fund_today": 0.173875,
      "pct_of_fund_prior": 0.167077,
      "pct_of_fund_change": 0.0068,
      "market_value_today": 64985.89
    },
    {
      "ticker": "CRM",
      "name": "SALESFORCE INC COMMON STOCK USD.001",
      "identifier": "79466L302",
      "sector": "",
      "status": "unchanged",
      "quantity_today": 109.0,
      "quantity_prior": 109.0,
      "quantity_pct_change": 0.0,
      "pct_of_fund_today": 0.05036,
      "pct_of_fund_prior": 0.048602,
      "pct_of_fund_change": 0.0018,
      "market_value_today": 18822.12
    },
    {
      "ticker": "CSCO",
      "name": "CISCO SYSTEMS INC COMMON STOCK USD.001",
      "identifier": "17275R102",
      "sector": "",
      "status": "unchanged",
      "quantity_today": 885.0,
      "quantity_prior": 885.0,
      "quantity_pct_change": 0.0,
      "pct_of_fund_today": 0.259663,
      "pct_of_fund_prior": 0.264104,
      "pct_of_fund_change": -0.0044,
      "market_value_today": 97049.1
    },
    {
      "ticker": "CTSH",
      "name": "COGNIZANT TECH SOLUTIONS A COMMON STOCK USD.01",
      "identifier": "192446102",
      "sector": "",
      "status": "unchanged",
      "quantity_today": 380.0,
      "quantity_prior": 380.0,
      "quantity_pct_change": 0.0,
      "pct_of_fund_today": 0.045305,
      "pct_of_fund_prior": 0.04381,
      "pct_of_fund_change": 0.0015,
      "market_value_today": 16932.8
    },
    {
      "ticker": "",
      "name": "Cash/Cash equivalent USD",
      "identifier": "",
      "sector": "",
      "status": "unchanged",
      "quantity_today": 0,
      "quantity_prior": 0,
      "quantity_pct_change": 0,
      "pct_of_fund_today": 6.203875,
      "pct_of_fund_prior": 6.190404,
      "pct_of_fund_change": 0.0135,
      "market_value_today": 2318698.25
    },
    {
      "ticker": "DUK",
      "name": "DUKE ENERGY CORP COMMON STOCK USD.001",
      "identifier": "26441C204",
      "sector": "",
      "status": "unchanged",
      "quantity_today": 661.0,
      "quantity_prior": 661.0,
      "quantity_pct_change": 0.0,
      "pct_of_fund_today": 0.223033,
      "pct_of_fund_prior": 0.219442,
      "pct_of_fund_change": 0.0036,
      "market_value_today": 83358.71
    },
    {
      "ticker": "EA",
      "name": "ELECTRONIC ARTS INC COMMON STOCK USD.01",
      "identifier": "285512109",
      "sector": "",
      "status": "unchanged",
      "quantity_today": 92.0,
      "quantity_prior": 92.0,
      "quantity_pct_change": 0.0,
      "pct_of_fund_today": 0.051161,
      "pct_of_fund_prior": 0.050913,
      "pct_of_fund_change": 0.0002,
      "market_value_today": 19121.28
    },
    {
      "ticker": "ED",
      "name": "CONSOLIDATED EDISON INC COMMON STOCK USD.1",
      "identifier": "209115104",
      "sector": "",
      "status": "unchanged",
      "quantity_today": 189.0,
      "quantity_prior": 189.0,
      "quantity_pct_change": 0.0,
      "pct_of_fund_today": 0.056834,
      "pct_of_fund_prior": 0.055665,
      "pct_of_fund_change": 0.0012,
      "market_value_today": 21241.71
    },
    {
      "ticker": "EHC",
      "name": "ENCOMPASS HEALTH CORP COMMON STOCK USD.01",
      "identifier": "29261A100",
      "sector": "",
      "status": "unchanged",
      "quantity_today": 162.0,
      "quantity_prior": 162.0,
      "quantity_pct_change": 0.0,
      "pct_of_fund_today": 0.048758,
      "pct_of_fund_prior": 0.047527,
      "pct_of_fund_change": 0.0012,
      "market_value_today": 18223.38
    },
    {
      "ticker": "ELV",
      "name": "ELEVANCE HEALTH INC COMMON STOCK USD.01",
      "identifier": "036752103",
      "sector": "",
      "status": "unchanged",
      "quantity_today": 53.0,
      "quantity_prior": 53.0,
      "quantity_pct_change": 0.0,
      "pct_of_fund_today": 0.052872,
      "pct_of_fund_prior": 0.055235,
      "pct_of_fund_change": -0.0024,
      "market_value_today": 19761.05
    },
    {
      "ticker": "EOG",
      "name": "EOG RESOURCES INC COMMON STOCK USD.01",
      "identifier": "26875P101",
      "sector": "",
      "status": "unchanged",
      "quantity_today": 354.0,
      "quantity_prior": 354.0,
      "quantity_pct_change": 0.0,
      "pct_of_fund_today": 0.131143,
      "pct_of_fund_prior": 0.129933,
      "pct_of_fund_change": 0.0012,
      "market_value_today": 49014.84
    },
    {
      "ticker": "EQIX",
      "name": "EQUINIX INC REIT USD.001",
      "identifier": "29444U700",
      "sector": "",
      "status": "unchanged",
      "quantity_today": 9.0,
      "quantity_prior": 9.0,
      "quantity_pct_change": 0.0,
      "pct_of_fund_today": 0.0243,
      "pct_of_fund_prior": 0.024573,
      "pct_of_fund_change": -0.0003,
      "market_value_today": 9082.26
    },
    {
      "ticker": "ESU26",
      "name": "S+P500 EMINI FUT  SEP26 XCME 20260918",
      "identifier": "ADI2VD0L0",
      "sector": "",
      "status": "unchanged",
      "quantity_today": -13.0,
      "quantity_prior": -13.0,
      "quantity_pct_change": -0.0,
      "pct_of_fund_today": -0.041752,
      "pct_of_fund_prior": -0.105878,
      "pct_of_fund_change": 0.0641,
      "market_value_today": -4925537.5
    },
    {
      "ticker": "FFIV",
      "name": "F5 INC COMMON STOCK",
      "identifier": "315616102",
      "sector": "",
      "status": "unchanged",
      "quantity_today": 115.0,
      "quantity_prior": 115.0,
      "quantity_pct_change": 0.0,
      "pct_of_fund_today": 0.124126,
      "pct_of_fund_prior": 0.129411,
      "pct_of_fund_change": -0.0053,
      "market_value_today": 46392.15
    },
    {
      "ticker": "FTNT",
      "name": "FORTINET INC COMMON STOCK USD.001",
      "identifier": "34959E109",
      "sector": "",
      "status": "unchanged",
      "quantity_today": 203.0,
      "quantity_prior": 203.0,
      "quantity_pct_change": 0.0,
      "pct_of_fund_today": 0.087327,
      "pct_of_fund_prior": 0.089165,
      "pct_of_fund_change": -0.0018,
      "market_value_today": 32638.34
    },
    {
      "ticker": "GILD",
      "name": "GILEAD SCIENCES INC COMMON STOCK USD.001",
      "identifier": "375558103",
      "sector": "",
      "status": "unchanged",
      "quantity_today": 566.0,
      "quantity_prior": 566.0,
      "quantity_pct_change": 0.0,
      "pct_of_fund_today": 0.20641,
      "pct_of_fund_prior": 0.199026,
      "pct_of_fund_change": 0.0074,
      "market_value_today": 77145.8
    },
    {
      "ticker": "GLW",
      "name": "CORNING INC COMMON STOCK USD.5",
      "identifier": "219350105",
      "sector": "",
      "status": "unchanged",
      "quantity_today": 83.0,
      "quantity_prior": 83.0,
      "quantity_pct_change": 0.0,
      "pct_of_fund_today": 0.035174,
      "pct_of_fund_prior": 0.038651,
      "pct_of_fund_change": -0.0035,
      "market_value_today": 13146.37
    },
    {
      "ticker": "GOOG",
      "name": "ALPHABET INC CL C COMMON STOCK USD.001",
      "identifier": "02079K107",
      "sector": "",
      "status": "unchanged",
      "quantity_today": 107.0,
      "quantity_prior": 107.0,
      "quantity_pct_change": 0.0,
      "pct_of_fund_today": 0.101291,
      "pct_of_fund_prior": 0.105764,
      "pct_of_fund_change": -0.0045,
      "market_value_today": 37857.67
    },
    {
      "ticker": "IBM",
      "name": "INTL BUSINESS MACHINES CORP COMMON STOCK USD.2",
      "identifier": "459200101",
      "sector": "",
      "status": "unchanged",
      "quantity_today": 153.0,
      "quantity_prior": 153.0,
      "quantity_pct_change": 0.0,
      "pct_of_fund_today": 0.089671,
      "pct_of_fund_prior": 0.086277,
      "pct_of_fund_change": 0.0034,
      "market_value_today": 33514.65
    },
    {
      "ticker": "ISRG",
      "name": "INTUITIVE SURGICAL INC COMMON STOCK USD.001",
      "identifier": "46120E602",
      "sector": "",
      "status": "unchanged",
      "quantity_today": 50.0,
      "quantity_prior": 50.0,
      "quantity_pct_change": 0.0,
      "pct_of_fund_today": 0.053823,
      "pct_of_fund_prior": 0.051927,
      "pct_of_fund_change": 0.0019,
      "market_value_today": 20116.5
    },
    {
      "ticker": "JNJ",
      "name": "JOHNSON + JOHNSON COMMON STOCK USD1.0",
      "identifier": "478160104",
      "sector": "",
      "status": "unchanged",
      "quantity_today": 312.0,
      "quantity_prior": 312.0,
      "quantity_pct_change": 0.0,
      "pct_of_fund_today": 0.208671,
      "pct_of_fund_prior": 0.205776,
      "pct_of_fund_change": 0.0029,
      "market_value_today": 77990.64
    },
    {
      "ticker": "KDP",
      "name": "KEURIG DR PEPPER INC COMMON STOCK USD.01",
      "identifier": "49271V100",
      "sector": "",
      "status": "unchanged",
      "quantity_today": 689.0,
      "quantity_prior": 689.0,
      "quantity_pct_change": 0.0,
      "pct_of_fund_today": 0.057848,
      "pct_of_fund_prior": 0.055703,
      "pct_of_fund_change": 0.0021,
      "market_value_today": 21620.82
    },
    {
      "ticker": "KO",
      "name": "COCA COLA CO/THE COMMON STOCK USD.25",
      "identifier": "191216100",
      "sector": "",
      "status": "unchanged",
      "quantity_today": 629.0,
      "quantity_prior": 629.0,
      "quantity_pct_change": 0.0,
      "pct_of_fund_today": 0.142916,
      "pct_of_fund_prior": 0.138468,
      "pct_of_fund_change": 0.0044,
      "market_value_today": 53414.68
    },
    {
      "ticker": "LIN",
      "name": "LINDE PLC COMMON STOCK",
      "identifier": "G54950103",
      "sector": "",
      "status": "unchanged",
      "quantity_today": 60.0,
      "quantity_prior": 60.0,
      "quantity_pct_change": 0.0,
      "pct_of_fund_today": 0.083597,
      "pct_of_fund_prior": 0.082366,
      "pct_of_fund_change": 0.0012,
      "market_value_today": 31244.4
    },
    {
      "ticker": "LLY",
      "name": "ELI LILLY + CO COMMON STOCK",
      "identifier": "532457108",
      "sector": "",
      "status": "unchanged",
      "quantity_today": 9.0,
      "quantity_prior": 9.0,
      "quantity_pct_change": 0.0,
      "pct_of_fund_today": 0.028154,
      "pct_of_fund_prior": 0.027794,
      "pct_of_fund_change": 0.0004,
      "market_value_today": 10522.53
    },
    {
      "ticker": "LMT",
      "name": "LOCKHEED MARTIN CORP COMMON STOCK USD1.0",
      "identifier": "539830109",
      "sector": "",
      "status": "unchanged",
      "quantity_today": 63.0,
      "quantity_prior": 63.0,
      "quantity_pct_change": 0.0,
      "pct_of_fund_today": 0.08656,
      "pct_of_fund_prior": 0.086537,
      "pct_of_fund_change": 0.0,
      "market_value_today": 32351.76
    },
    {
      "ticker": "MA",
      "name": "MASTERCARD INC   A COMMON STOCK USD.0001",
      "identifier": "57636Q104",
      "sector": "",
      "status": "unchanged",
      "quantity_today": 144.0,
      "quantity_prior": 144.0,
      "quantity_pct_change": 0.0,
      "pct_of_fund_today": 0.2125,
      "pct_of_fund_prior": 0.205776,
      "pct_of_fund_change": 0.0067,
      "market_value_today": 79421.76
    },
    {
      "ticker": "MCD",
      "name": "MCDONALD S CORP COMMON STOCK USD.01",
      "identifier": "580135101",
      "sector": "",
      "status": "unchanged",
      "quantity_today": 257.0,
      "quantity_prior": 257.0,
      "quantity_pct_change": 0.0,
      "pct_of_fund_today": 0.188038,
      "pct_of_fund_prior": 0.181804,
      "pct_of_fund_change": 0.0062,
      "market_value_today": 70279.22
    },
    {
      "ticker": "MCK",
      "name": "MCKESSON CORP COMMON STOCK USD.01",
      "identifier": "58155Q103",
      "sector": "",
      "status": "unchanged",
      "quantity_today": 103.0,
      "quantity_prior": 103.0,
      "quantity_pct_change": 0.0,
      "pct_of_fund_today": 0.231853,
      "pct_of_fund_prior": 0.219002,
      "pct_of_fund_change": 0.0129,
      "market_value_today": 86654.93
    },
    {
      "ticker": "META",
      "name": "META PLATFORMS INC CLASS A COMMON STOCK USD.000006",
      "identifier": "30303M102",
      "sector": "",
      "status": "unchanged",
      "quantity_today": 27.0,
      "quantity_prior": 27.0,
      "quantity_pct_change": 0.0,
      "pct_of_fund_today": 0.048007,
      "pct_of_fund_prior": 0.049115,
      "pct_of_fund_change": -0.0011,
      "market_value_today": 17942.58
    },
    {
      "ticker": "MRK",
      "name": "MERCK + CO. INC. COMMON STOCK USD.5",
      "identifier": "58933Y105",
      "sector": "",
      "status": "unchanged",
      "quantity_today": 682.0,
      "quantity_prior": 682.0,
      "quantity_pct_change": 0.0,
      "pct_of_fund_today": 0.232893,
      "pct_of_fund_prior": 0.225084,
      "pct_of_fund_change": 0.0078,
      "market_value_today": 87043.66
    },
    {
      "ticker": "MRSH",
      "name": "MARSH + MCLENNAN COS COMMON STOCK USD1.0",
      "identifier": "571748102",
      "sector": "",
      "status": "unchanged",
      "quantity_today": 249.0,
      "quantity_prior": 249.0,
      "quantity_pct_change": 0.0,
      "pct_of_fund_today": 0.121352,
      "pct_of_fund_prior": 0.117155,
      "pct_of_fund_change": 0.0042,
      "market_value_today": 45355.35
    },
    {
      "ticker": "MSFT",
      "name": "MICROSOFT CORP COMMON STOCK USD.00000625",
      "identifier": "594918104",
      "sector": "",
      "status": "unchanged",
      "quantity_today": 199.0,
      "quantity_prior": 199.0,
      "quantity_pct_change": 0.0,
      "pct_of_fund_today": 0.213562,
      "pct_of_fund_prior": 0.210208,
      "pct_of_fund_change": 0.0034,
      "market_value_today": 79818.9
    },
    {
      "ticker": "MSI",
      "name": "MOTOROLA SOLUTIONS INC COMMON STOCK USD.01",
      "identifier": "620076307",
      "sector": "",
      "status": "unchanged",
      "quantity_today": 228.0,
      "quantity_prior": 228.0,
      "quantity_pct_change": 0.0,
      "pct_of_fund_today": 0.25267,
      "pct_of_fund_prior": 0.247873,
      "pct_of_fund_change": 0.0048,
      "market_value_today": 94435.32
    },
    {
      "ticker": "MU",
      "name": "MICRON TECHNOLOGY INC COMMON STOCK USD.1",
      "identifier": "595112103",
      "sector": "",
      "status": "unchanged",
      "quantity_today": 10.0,
      "quantity_prior": 10.0,
      "quantity_pct_change": 0.0,
      "pct_of_fund_today": 0.022828,
      "pct_of_fund_prior": 0.024144,
      "pct_of_fund_change": -0.0013,
      "market_value_today": 8532.0
    },
    {
      "ticker": "NEM",
      "name": "NEWMONT CORP COMMON STOCK USD1.6",
      "identifier": "651639106",
      "sector": "",
      "status": "unchanged",
      "quantity_today": 115.0,
      "quantity_prior": 115.0,
      "quantity_pct_change": 0.0,
      "pct_of_fund_today": 0.027948,
      "pct_of_fund_prior": 0.029234,
      "pct_of_fund_change": -0.0013,
      "market_value_today": 10445.45
    },
    {
      "ticker": "NFLX",
      "name": "NETFLIX INC COMMON STOCK USD.001",
      "identifier": "64110L106",
      "sector": "",
      "status": "unchanged",
      "quantity_today": 285.0,
      "quantity_prior": 285.0,
      "quantity_pct_change": 0.0,
      "pct_of_fund_today": 0.056695,
      "pct_of_fund_prior": 0.056066,
      "pct_of_fund_change": 0.0006,
      "market_value_today": 21189.75
    },
    {
      "ticker": "NOC",
      "name": "NORTHROP GRUMMAN CORP COMMON STOCK USD1.0",
      "identifier": "666807102",
      "sector": "",
      "status": "unchanged",
      "quantity_today": 45.0,
      "quantity_prior": 45.0,
      "quantity_pct_change": 0.0,
      "pct_of_fund_today": 0.062446,
      "pct_of_fund_prior": 0.063105,
      "pct_of_fund_change": -0.0007,
      "market_value_today": 23339.25
    },
    {
      "ticker": "NOW",
      "name": "SERVICENOW INC COMMON STOCK USD.001",
      "identifier": "81762P102",
      "sector": "",
      "status": "unchanged",
      "quantity_today": 488.0,
      "quantity_prior": 488.0,
      "quantity_pct_change": 0.0,
      "pct_of_fund_today": 0.135804,
      "pct_of_fund_prior": 0.136458,
      "pct_of_fund_change": -0.0007,
      "market_value_today": 50756.88
    },
    {
      "ticker": "NTAP",
      "name": "NETAPP INC COMMON STOCK USD.001",
      "identifier": "64110D104",
      "sector": "",
      "status": "unchanged",
      "quantity_today": 108.0,
      "quantity_prior": 108.0,
      "quantity_pct_change": 0.0,
      "pct_of_fund_today": 0.046145,
      "pct_of_fund_prior": 0.046743,
      "pct_of_fund_change": -0.0006,
      "market_value_today": 17246.52
    },
    {
      "ticker": "NVDA",
      "name": "NVIDIA CORP COMMON STOCK USD.001",
      "identifier": "67066G104",
      "sector": "",
      "status": "unchanged",
      "quantity_today": 406.0,
      "quantity_prior": 406.0,
      "quantity_pct_change": 0.0,
      "pct_of_fund_today": 0.225296,
      "pct_of_fund_prior": 0.230352,
      "pct_of_fund_change": -0.0051,
      "market_value_today": 84204.4
    },
    {
      "ticker": "ORCL",
      "name": "ORACLE CORP COMMON STOCK USD.01",
      "identifier": "68389X105",
      "sector": "",
      "status": "unchanged",
      "quantity_today": 14.0,
      "quantity_prior": 14.0,
      "quantity_pct_change": 0.0,
      "pct_of_fund_today": 0.004653,
      "pct_of_fund_prior": 0.004952,
      "pct_of_fund_change": -0.0003,
      "market_value_today": 1738.94
    },
    {
      "ticker": "ORLY",
      "name": "O REILLY AUTOMOTIVE INC COMMON STOCK USD.01",
      "identifier": "67103H107",
      "sector": "",
      "status": "unchanged",
      "quantity_today": 557.0,
      "quantity_prior": 557.0,
      "quantity_pct_change": 0.0,
      "pct_of_fund_today": 0.128538,
      "pct_of_fund_prior": 0.123034,
      "pct_of_fund_change": 0.0055,
      "market_value_today": 48041.25
    },
    {
      "ticker": "PANW",
      "name": "PALO ALTO NETWORKS INC COMMON STOCK USD.0001",
      "identifier": "697435105",
      "sector": "",
      "status": "unchanged",
      "quantity_today": 59.0,
      "quantity_prior": 59.0,
      "quantity_pct_change": 0.0,
      "pct_of_fund_today": 0.055881,
      "pct_of_fund_prior": 0.055768,
      "pct_of_fund_change": 0.0001,
      "market_value_today": 20885.41
    },
    {
      "ticker": "PEP",
      "name": "PEPSICO INC COMMON STOCK USD.017",
      "identifier": "713448108",
      "sector": "",
      "status": "unchanged",
      "quantity_today": 158.0,
      "quantity_prior": 158.0,
      "quantity_pct_change": 0.0,
      "pct_of_fund_today": 0.058943,
      "pct_of_fund_prior": 0.057119,
      "pct_of_fund_change": 0.0018,
      "market_value_today": 22029.94
    },
    {
      "ticker": "PG",
      "name": "PROCTER + GAMBLE CO/THE COMMON STOCK",
      "identifier": "742718109",
      "sector": "",
      "status": "unchanged",
      "quantity_today": 494.0,
      "quantity_prior": 494.0,
      "quantity_pct_change": 0.0,
      "pct_of_fund_today": 0.200243,
      "pct_of_fund_prior": 0.195273,
      "pct_of_fund_change": 0.005,
      "market_value_today": 74841.0
    },
    {
      "ticker": "PGR",
      "name": "PROGRESSIVE CORP COMMON STOCK USD1.0",
      "identifier": "743315103",
      "sector": "",
      "status": "unchanged",
      "quantity_today": 148.0,
      "quantity_prior": 148.0,
      "quantity_pct_change": 0.0,
      "pct_of_fund_today": 0.081494,
      "pct_of_fund_prior": 0.081094,
      "pct_of_fund_change": 0.0004,
      "market_value_today": 30458.4
    },
    {
      "ticker": "PH",
      "name": "PARKER HANNIFIN CORP COMMON STOCK USD.5",
      "identifier": "701094104",
      "sector": "",
      "status": "unchanged",
      "quantity_today": 8.0,
      "quantity_prior": 8.0,
      "quantity_pct_change": 0.0,
      "pct_of_fund_today": 0.020513,
      "pct_of_fund_prior": 0.020355,
      "pct_of_fund_change": 0.0002,
      "market_value_today": 7666.72
    },
    {
      "ticker": "PM",
      "name": "PHILIP MORRIS INTERNATIONAL COMMON STOCK",
      "identifier": "718172109",
      "sector": "",
      "status": "unchanged",
      "quantity_today": 355.0,
      "quantity_prior": 355.0,
      "quantity_pct_change": 0.0,
      "pct_of_fund_today": 0.180316,
      "pct_of_fund_prior": 0.171446,
      "pct_of_fund_change": 0.0089,
      "market_value_today": 67393.2
    },
    {
      "ticker": "PSA",
      "name": "PUBLIC STORAGE REIT USD.1",
      "identifier": "74460D109",
      "sector": "",
      "status": "unchanged",
      "quantity_today": 41.0,
      "quantity_prior": 41.0,
      "quantity_pct_change": 0.0,
      "pct_of_fund_today": 0.035597,
      "pct_of_fund_prior": 0.034448,
      "pct_of_fund_change": 0.0011,
      "market_value_today": 13304.5
    },
    {
      "ticker": "PTC",
      "name": "PTC INC COMMON STOCK USD.01",
      "identifier": "69370C100",
      "sector": "",
      "status": "unchanged",
      "quantity_today": 235.0,
      "quantity_prior": 235.0,
      "quantity_pct_change": 0.0,
      "pct_of_fund_today": 0.080079,
      "pct_of_fund_prior": 0.077558,
      "pct_of_fund_change": 0.0025,
      "market_value_today": 29929.6
    },
    {
      "ticker": "REGN",
      "name": "REGENERON PHARMACEUTICALS COMMON STOCK USD.001",
      "identifier": "75886F107",
      "sector": "",
      "status": "unchanged",
      "quantity_today": 36.0,
      "quantity_prior": 36.0,
      "quantity_pct_change": 0.0,
      "pct_of_fund_today": 0.065396,
      "pct_of_fund_prior": 0.063866,
      "pct_of_fund_change": 0.0015,
      "market_value_today": 24441.84
    },
    {
      "ticker": "RMD",
      "name": "RESMED INC COMMON STOCK USD.004",
      "identifier": "761152107",
      "sector": "",
      "status": "unchanged",
      "quantity_today": 114.0,
      "quantity_prior": 114.0,
      "quantity_pct_change": 0.0,
      "pct_of_fund_today": 0.061845,
      "pct_of_fund_prior": 0.06044,
      "pct_of_fund_change": 0.0014,
      "market_value_today": 23114.64
    },
    {
      "ticker": "ROP",
      "name": "ROPER TECHNOLOGIES INC COMMON STOCK USD.01",
      "identifier": "776696106",
      "sector": "",
      "status": "unchanged",
      "quantity_today": 110.0,
      "quantity_prior": 110.0,
      "quantity_pct_change": 0.0,
      "pct_of_fund_today": 0.107192,
      "pct_of_fund_prior": 0.102356,
      "pct_of_fund_change": 0.0048,
      "market_value_today": 40063.1
    },
    {
      "ticker": "RSG",
      "name": "REPUBLIC SERVICES INC COMMON STOCK USD.01",
      "identifier": "760759100",
      "sector": "",
      "status": "unchanged",
      "quantity_today": 207.0,
      "quantity_prior": 207.0,
      "quantity_pct_change": 0.0,
      "pct_of_fund_today": 0.124344,
      "pct_of_fund_prior": 0.120121,
      "pct_of_fund_change": 0.0042,
      "market_value_today": 46473.57
    },
    {
      "ticker": "SO",
      "name": "SOUTHERN CO/THE COMMON STOCK USD5.0",
      "identifier": "842587107",
      "sector": "",
      "status": "unchanged",
      "quantity_today": 411.0,
      "quantity_prior": 411.0,
      "quantity_pct_change": 0.0,
      "pct_of_fund_today": 0.105645,
      "pct_of_fund_prior": 0.10381,
      "pct_of_fund_change": 0.0018,
      "market_value_today": 39484.77
    },
    {
      "ticker": "SPX   270521P06400000",
      "name": "S+P 500 INDEX MAY27 6400 PUT",
      "identifier": "ADI39X8Q0",
      "sector": "",
      "status": "unchanged",
      "quantity_today": 2.0,
      "quantity_prior": 2.0,
      "quantity_pct_change": 0.0,
      "pct_of_fund_today": 0.084896,
      "pct_of_fund_prior": 0.08066,
      "pct_of_fund_change": 0.0042,
      "market_value_today": 31730.0
    },
    {
      "ticker": "SPX   270617P06500000",
      "name": "S+P 500 INDEX JUN27 6500 PUT",
      "identifier": "ADI3B90V7",
      "sector": "",
      "status": "unchanged",
      "quantity_today": 2.0,
      "quantity_prior": 2.0,
      "quantity_pct_change": 0.0,
      "pct_of_fund_today": 0.099104,
      "pct_of_fund_prior": 0.094571,
      "pct_of_fund_change": 0.0045,
      "market_value_today": 37040.0
    },
    {
      "ticker": "SPX   270716P06600000",
      "name": "S+P 500 INDEX JUL27 6600 PUT",
      "identifier": "ADI3BQTF3",
      "sector": "",
      "status": "unchanged",
      "quantity_today": 2.0,
      "quantity_prior": 2.0,
      "quantity_pct_change": 0.0,
      "pct_of_fund_today": 0.114542,
      "pct_of_fund_prior": 0.109469,
      "pct_of_fund_change": 0.0051,
      "market_value_today": 42810.0
    },
    {
      "ticker": "SSNC",
      "name": "SS+C TECHNOLOGIES HOLDINGS COMMON STOCK USD.01",
      "identifier": "78467J100",
      "sector": "",
      "status": "unchanged",
      "quantity_today": 308.0,
      "quantity_prior": 308.0,
      "quantity_pct_change": 0.0,
      "pct_of_fund_today": 0.058155,
      "pct_of_fund_prior": 0.056405,
      "pct_of_fund_change": 0.0018,
      "market_value_today": 21735.56
    },
    {
      "ticker": "T",
      "name": "AT+T INC COMMON STOCK USD1.0",
      "identifier": "00206R102",
      "sector": "",
      "status": "unchanged",
      "quantity_today": 1351.0,
      "quantity_prior": 1351.0,
      "quantity_pct_change": 0.0,
      "pct_of_fund_today": 0.079451,
      "pct_of_fund_prior": 0.077301,
      "pct_of_fund_change": 0.0021,
      "market_value_today": 29694.98
    },
    {
      "ticker": "TDY",
      "name": "TELEDYNE TECHNOLOGIES INC COMMON STOCK USD.01",
      "identifier": "879360105",
      "sector": "",
      "status": "unchanged",
      "quantity_today": 114.0,
      "quantity_prior": 114.0,
      "quantity_pct_change": 0.0,
      "pct_of_fund_today": 0.192423,
      "pct_of_fund_prior": 0.189977,
      "pct_of_fund_change": 0.0024,
      "market_value_today": 71918.04
    },
    {
      "ticker": "TEL",
      "name": "TE CONNECTIVITY PLC COMMON STOCK USD.01",
      "identifier": "G87052109",
      "sector": "",
      "status": "unchanged",
      "quantity_today": 206.0,
      "quantity_prior": 206.0,
      "quantity_pct_change": 0.0,
      "pct_of_fund_today": 0.111651,
      "pct_of_fund_prior": 0.11074,
      "pct_of_fund_change": 0.0009,
      "market_value_today": 41729.42
    },
    {
      "ticker": "TJX",
      "name": "TJX COMPANIES INC COMMON STOCK USD1.0",
      "identifier": "872540109",
      "sector": "",
      "status": "unchanged",
      "quantity_today": 467.0,
      "quantity_prior": 467.0,
      "quantity_pct_change": 0.0,
      "pct_of_fund_today": 0.19341,
      "pct_of_fund_prior": 0.188241,
      "pct_of_fund_change": 0.0052,
      "market_value_today": 72286.93
    },
    {
      "ticker": "TMUS",
      "name": "T MOBILE US INC COMMON STOCK USD.0001",
      "identifier": "872590104",
      "sector": "",
      "status": "unchanged",
      "quantity_today": 451.0,
      "quantity_prior": 451.0,
      "quantity_pct_change": 0.0,
      "pct_of_fund_today": 0.23271,
      "pct_of_fund_prior": 0.225924,
      "pct_of_fund_change": 0.0068,
      "market_value_today": 86975.35
    },
    {
      "ticker": "",
      "name": "TREASURY BILL 08/26 0.00000",
      "identifier": "912797TW7",
      "sector": "",
      "status": "unchanged",
      "quantity_today": 40000.0,
      "quantity_prior": 40000.0,
      "quantity_pct_change": 0.0,
      "pct_of_fund_today": 0.106733,
      "pct_of_fund_prior": 0.106499,
      "pct_of_fund_change": 0.0002,
      "market_value_today": 39891.49
    },
    {
      "ticker": "",
      "name": "TREASURY BILL 09/26 0.00000",
      "identifier": "912797UF2",
      "sector": "",
      "status": "unchanged",
      "quantity_today": 130000.0,
      "quantity_prior": 130000.0,
      "quantity_pct_change": 0.0,
      "pct_of_fund_today": 0.345895,
      "pct_of_fund_prior": 0.345147,
      "pct_of_fund_change": 0.0007,
      "market_value_today": 129278.35
    },
    {
      "ticker": "",
      "name": "TREASURY BILL 10/26 0.00000",
      "identifier": "912797UK1",
      "sector": "",
      "status": "unchanged",
      "quantity_today": 130000.0,
      "quantity_prior": 130000.0,
      "quantity_pct_change": 0.0,
      "pct_of_fund_today": 0.34461,
      "pct_of_fund_prior": 0.343851,
      "pct_of_fund_change": 0.0008,
      "market_value_today": 128797.85
    },
    {
      "ticker": "TRV",
      "name": "TRAVELERS COS INC/THE COMMON STOCK",
      "identifier": "89417E109",
      "sector": "",
      "status": "unchanged",
      "quantity_today": 88.0,
      "quantity_prior": 88.0,
      "quantity_pct_change": 0.0,
      "pct_of_fund_today": 0.07954,
      "pct_of_fund_prior": 0.077346,
      "pct_of_fund_change": 0.0022,
      "market_value_today": 29728.16
    },
    {
      "ticker": "TSPA",
      "name": "T ROWE PRICE US EQUITY RESEARC T ROWE PRICE US EQY RESEARCH",
      "identifier": "87283Q503",
      "sector": "",
      "status": "unchanged",
      "quantity_today": 643780.0,
      "quantity_prior": 643780.0,
      "quantity_pct_change": 0.0,
      "pct_of_fund_today": 81.835426,
      "pct_of_fund_prior": 82.076355,
      "pct_of_fund_change": -0.2409,
      "market_value_today": 30585987.8
    },
    {
      "ticker": "TXN",
      "name": "TEXAS INSTRUMENTS INC COMMON STOCK USD1.0",
      "identifier": "882508104",
      "sector": "",
      "status": "unchanged",
      "quantity_today": 56.0,
      "quantity_prior": 56.0,
      "quantity_pct_change": 0.0,
      "pct_of_fund_today": 0.043634,
      "pct_of_fund_prior": 0.045034,
      "pct_of_fund_change": -0.0014,
      "market_value_today": 16308.32
    },
    {
      "ticker": "TYU26",
      "name": "US 10YR NOTE (CBT)SEP26 XCBT 20260921",
      "identifier": "ADI38FH49",
      "sector": "",
      "status": "unchanged",
      "quantity_today": 43.0,
      "quantity_prior": 43.0,
      "quantity_pct_change": 0.0,
      "pct_of_fund_today": 0.012671,
      "pct_of_fund_prior": 0.030583,
      "pct_of_fund_change": -0.0179,
      "market_value_today": 4693046.88
    },
    {
      "ticker": "ULTA",
      "name": "ULTA BEAUTY INC COMMON STOCK",
      "identifier": "90384S303",
      "sector": "",
      "status": "unchanged",
      "quantity_today": 21.0,
      "quantity_prior": 21.0,
      "quantity_pct_change": 0.0,
      "pct_of_fund_today": 0.026906,
      "pct_of_fund_prior": 0.026136,
      "pct_of_fund_change": 0.0008,
      "market_value_today": 10056.06
    },
    {
      "ticker": "UNH",
      "name": "UNITEDHEALTH GROUP INC COMMON STOCK USD.01",
      "identifier": "91324P102",
      "sector": "",
      "status": "unchanged",
      "quantity_today": 90.0,
      "quantity_prior": 90.0,
      "quantity_pct_change": 0.0,
      "pct_of_fund_today": 0.101951,
      "pct_of_fund_prior": 0.100569,
      "pct_of_fund_change": 0.0014,
      "market_value_today": 38104.2
    },
    {
      "ticker": "UTHR",
      "name": "UNITED THERAPEUTICS CORP COMMON STOCK USD.01",
      "identifier": "91307C102",
      "sector": "",
      "status": "unchanged",
      "quantity_today": 38.0,
      "quantity_prior": 38.0,
      "quantity_pct_change": 0.0,
      "pct_of_fund_today": 0.05379,
      "pct_of_fund_prior": 0.053955,
      "pct_of_fund_change": -0.0002,
      "market_value_today": 20103.9
    },
    {
      "ticker": "V",
      "name": "VISA INC CLASS A SHARES COMMON STOCK USD.0001",
      "identifier": "92826C839",
      "sector": "",
      "status": "unchanged",
      "quantity_today": 203.0,
      "quantity_prior": 203.0,
      "quantity_pct_change": 0.0,
      "pct_of_fund_today": 0.198324,
      "pct_of_fund_prior": 0.192488,
      "pct_of_fund_change": 0.0058,
      "market_value_today": 74123.42
    },
    {
      "ticker": "VRSK",
      "name": "VERISK ANALYTICS INC COMMON STOCK USD.001",
      "identifier": "92345Y106",
      "sector": "",
      "status": "unchanged",
      "quantity_today": 141.0,
      "quantity_prior": 141.0,
      "quantity_pct_change": 0.0,
      "pct_of_fund_today": 0.076014,
      "pct_of_fund_prior": 0.072259,
      "pct_of_fund_change": 0.0038,
      "market_value_today": 28410.09
    },
    {
      "ticker": "VRSN",
      "name": "VERISIGN INC COMMON STOCK USD.001",
      "identifier": "92343E102",
      "sector": "",
      "status": "unchanged",
      "quantity_today": 139.0,
      "quantity_prior": 139.0,
      "quantity_pct_change": 0.0,
      "pct_of_fund_today": 0.102356,
      "pct_of_fund_prior": 0.100397,
      "pct_of_fund_change": 0.002,
      "market_value_today": 38255.58
    },
    {
      "ticker": "VRTX",
      "name": "VERTEX PHARMACEUTICALS INC COMMON STOCK USD.01",
      "identifier": "92532F100",
      "sector": "",
      "status": "unchanged",
      "quantity_today": 6.0,
      "quantity_prior": 6.0,
      "quantity_pct_change": 0.0,
      "pct_of_fund_today": 0.007802,
      "pct_of_fund_prior": 0.007643,
      "pct_of_fund_change": 0.0002,
      "market_value_today": 2916.18
    },
    {
      "ticker": "VZ",
      "name": "VERIZON COMMUNICATIONS INC COMMON STOCK USD.1",
      "identifier": "92343V104",
      "sector": "",
      "status": "unchanged",
      "quantity_today": 1352.0,
      "quantity_prior": 1352.0,
      "quantity_pct_change": 0.0,
      "pct_of_fund_today": 0.158731,
      "pct_of_fund_prior": 0.154608,
      "pct_of_fund_change": 0.0041,
      "market_value_today": 59325.76
    },
    {
      "ticker": "WCN",
      "name": "WASTE CONNECTIONS INC COMMON STOCK",
      "identifier": "94106B101",
      "sector": "",
      "status": "unchanged",
      "quantity_today": 336.0,
      "quantity_prior": 336.0,
      "quantity_pct_change": 0.0,
      "pct_of_fund_today": 0.156722,
      "pct_of_fund_prior": 0.152617,
      "pct_of_fund_change": 0.0041,
      "market_value_today": 58574.88
    },
    {
      "ticker": "WDAY",
      "name": "WORKDAY INC CLASS A COMMON STOCK USD.001",
      "identifier": "98138H101",
      "sector": "",
      "status": "unchanged",
      "quantity_today": 238.0,
      "quantity_prior": 238.0,
      "quantity_pct_change": 0.0,
      "pct_of_fund_today": 0.092608,
      "pct_of_fund_prior": 0.09012,
      "pct_of_fund_change": 0.0025,
      "market_value_today": 34612.34
    },
    {
      "ticker": "WEC",
      "name": "WEC ENERGY GROUP INC COMMON STOCK USD.01",
      "identifier": "92939U106",
      "sector": "",
      "status": "unchanged",
      "quantity_today": 54.0,
      "quantity_prior": 54.0,
      "quantity_pct_change": 0.0,
      "pct_of_fund_today": 0.016542,
      "pct_of_fund_prior": 0.016288,
      "pct_of_fund_change": 0.0003,
      "market_value_today": 6182.46
    },
    {
      "ticker": "WELL",
      "name": "WELLTOWER INC REIT USD1.0",
      "identifier": "95040Q104",
      "sector": "",
      "status": "unchanged",
      "quantity_today": 70.0,
      "quantity_prior": 70.0,
      "quantity_pct_change": 0.0,
      "pct_of_fund_today": 0.045229,
      "pct_of_fund_prior": 0.043601,
      "pct_of_fund_change": 0.0016,
      "market_value_today": 16904.3
    },
    {
      "ticker": "WM",
      "name": "WASTE MANAGEMENT INC COMMON STOCK USD.01",
      "identifier": "94106L109",
      "sector": "",
      "status": "unchanged",
      "quantity_today": 195.0,
      "quantity_prior": 195.0,
      "quantity_pct_change": 0.0,
      "pct_of_fund_today": 0.126391,
      "pct_of_fund_prior": 0.121206,
      "pct_of_fund_change": 0.0052,
      "market_value_today": 47238.75
    },
    {
      "ticker": "WMB",
      "name": "WILLIAMS COS INC COMMON STOCK USD1.0",
      "identifier": "969457100",
      "sector": "",
      "status": "unchanged",
      "quantity_today": 360.0,
      "quantity_prior": 360.0,
      "quantity_pct_change": 0.0,
      "pct_of_fund_today": 0.071981,
      "pct_of_fund_prior": 0.071493,
      "pct_of_fund_change": 0.0005,
      "market_value_today": 26902.8
    },
    {
      "ticker": "WMT",
      "name": "WALMART INC COMMON STOCK USD.1",
      "identifier": "931142103",
      "sector": "",
      "status": "unchanged",
      "quantity_today": 184.0,
      "quantity_prior": 184.0,
      "quantity_pct_change": 0.0,
      "pct_of_fund_today": 0.056591,
      "pct_of_fund_prior": 0.055283,
      "pct_of_fund_change": 0.0013,
      "market_value_today": 21150.8
    },
    {
      "ticker": "XEL",
      "name": "XCEL ENERGY INC COMMON STOCK USD2.5",
      "identifier": "98389B100",
      "sector": "",
      "status": "unchanged",
      "quantity_today": 461.0,
      "quantity_prior": 461.0,
      "quantity_pct_change": 0.0,
      "pct_of_fund_today": 0.098651,
      "pct_of_fund_prior": 0.097546,
      "pct_of_fund_change": 0.0011,
      "market_value_today": 36870.78
    },
    {
      "ticker": "XOM",
      "name": "EXXONMOBIL HOLDINGS CORP COMMON STOCK",
      "identifier": "30233Q108",
      "sector": "",
      "status": "unchanged",
      "quantity_today": 609.0,
      "quantity_prior": 609.0,
      "quantity_pct_change": 0.0,
      "pct_of_fund_today": 0.237816,
      "pct_of_fund_prior": 0.234975,
      "pct_of_fund_change": 0.0028,
      "market_value_today": 88883.55
    },
    {
      "ticker": "XYL",
      "name": "XYLEM INC COMMON STOCK",
      "identifier": "98419M100",
      "sector": "",
      "status": "unchanged",
      "quantity_today": 71.0,
      "quantity_prior": 71.0,
      "quantity_pct_change": 0.0,
      "pct_of_fund_today": 0.023803,
      "pct_of_fund_prior": 0.023019,
      "pct_of_fund_change": 0.0008,
      "market_value_today": 8896.3
    },
    {
      "ticker": "YUM",
      "name": "YUM  BRANDS INC COMMON STOCK",
      "identifier": "988498101",
      "sector": "",
      "status": "unchanged",
      "quantity_today": 117.0,
      "quantity_prior": 117.0,
      "quantity_pct_change": 0.0,
      "pct_of_fund_today": 0.047614,
      "pct_of_fund_prior": 0.047661,
      "pct_of_fund_change": -0.0,
      "market_value_today": 17795.7
    },
    {
      "ticker": "ZM",
      "name": "ZOOM COMMUNICATIONS INC COMMON STOCK USD.001",
      "identifier": "98980L101",
      "sector": "",
      "status": "unchanged",
      "quantity_today": 197.0,
      "quantity_prior": 197.0,
      "quantity_pct_change": 0.0,
      "pct_of_fund_today": 0.048977,
      "pct_of_fund_prior": 0.048706,
      "pct_of_fund_change": 0.0003,
      "market_value_today": 18305.24
    }
  ]
}