{
  "date": "2026-07-23",
  "ticker": "TGLB",
  "holdings": [
    {
      "name": "EURO CURRENCY",
      "ticker": "",
      "identifier": "999EURZ94",
      "pct_of_fund": 5.7e-05,
      "quantity": 12.44,
      "market_value": 14.19,
      "investments": "",
      "options_strike": 0.0,
      "sector": ""
    },
    {
      "name": "POUND STERLING",
      "ticker": "",
      "identifier": "999GBPZ94",
      "pct_of_fund": 0.0,
      "quantity": 0.02,
      "market_value": 0.03,
      "investments": "",
      "options_strike": 0.0,
      "sector": ""
    },
    {
      "name": "HONG KONG DOLLAR",
      "ticker": "",
      "identifier": "999HKDZ99",
      "pct_of_fund": 0,
      "quantity": 0.01,
      "market_value": 0.0,
      "investments": "",
      "options_strike": 0.0,
      "sector": ""
    },
    {
      "name": "JAPANESE YEN",
      "ticker": "",
      "identifier": "999JPYZ94",
      "pct_of_fund": 0.000616,
      "quantity": 24935.0,
      "market_value": 152.83,
      "investments": "",
      "options_strike": 0.0,
      "sector": ""
    },
    {
      "name": "SWEDISH KRONA",
      "ticker": "",
      "identifier": "999SEKZ96",
      "pct_of_fund": 0.015948,
      "quantity": 38388.12,
      "market_value": 3957.6,
      "investments": "",
      "options_strike": 0.0,
      "sector": ""
    },
    {
      "name": "EUR Spot FX Contract",
      "ticker": "",
      "identifier": "EUR999999",
      "pct_of_fund": -0.000163,
      "quantity": -144732.69,
      "market_value": -40.49,
      "investments": "",
      "options_strike": 0.0,
      "sector": ""
    },
    {
      "name": "EUR Spot FX Contract",
      "ticker": "",
      "identifier": "EUR999999",
      "pct_of_fund": -0.000267,
      "quantity": -237141.86,
      "market_value": -66.33,
      "investments": "",
      "options_strike": 0.0,
      "sector": ""
    },
    {
      "name": "ASTRAZENECA PLC COMMON STOCK USD.25",
      "ticker": "AZN",
      "identifier": "098952906",
      "pct_of_fund": 0.883605,
      "quantity": 1295.0,
      "market_value": 219276.76,
      "investments": "LT",
      "options_strike": 0.0,
      "sector": ""
    },
    {
      "name": "AMAZON.COM INC COMMON STOCK USD.01",
      "ticker": "AMZN",
      "identifier": "023135106",
      "pct_of_fund": 1.538196,
      "quantity": 1559.0,
      "market_value": 381721.15,
      "investments": "LT",
      "options_strike": 0.0,
      "sector": ""
    },
    {
      "name": "ADVANCED MICRO DEVICES COMMON STOCK USD.01",
      "ticker": "AMD",
      "identifier": "007903107",
      "pct_of_fund": 5.110176,
      "quantity": 2296.0,
      "market_value": 1268149.68,
      "investments": "LT",
      "options_strike": 0.0,
      "sector": ""
    },
    {
      "name": "APPLE INC COMMON STOCK USD.00001",
      "ticker": "AAPL",
      "identifier": "037833100",
      "pct_of_fund": 4.190474,
      "quantity": 3191.0,
      "market_value": 1039914.99,
      "investments": "LT",
      "options_strike": 0.0,
      "sector": ""
    },
    {
      "name": "AMEREN CORPORATION COMMON STOCK USD.01",
      "ticker": "AEE",
      "identifier": "023608102",
      "pct_of_fund": 0.912197,
      "quantity": 2021.0,
      "market_value": 226372.21,
      "investments": "LT",
      "options_strike": 0.0,
      "sector": ""
    },
    {
      "name": "AMPHENOL CORP CL A COMMON STOCK USD.001",
      "ticker": "APH",
      "identifier": "032095101",
      "pct_of_fund": 2.179585,
      "quantity": 3434.0,
      "market_value": 540889.34,
      "investments": "LT",
      "options_strike": 0.0,
      "sector": ""
    },
    {
      "name": "JPMORGAN CHASE + CO COMMON STOCK USD1.0",
      "ticker": "JPM",
      "identifier": "46625H100",
      "pct_of_fund": 1.709046,
      "quantity": 1218.0,
      "market_value": 424119.78,
      "investments": "LT",
      "options_strike": 0.0,
      "sector": ""
    },
    {
      "name": "CISCO SYSTEMS INC COMMON STOCK USD.001",
      "ticker": "CSCO",
      "identifier": "17275R102",
      "pct_of_fund": 1.512944,
      "quantity": 3346.0,
      "market_value": 375454.66,
      "investments": "LT",
      "options_strike": 0.0,
      "sector": ""
    },
    {
      "name": "DANAHER CORP COMMON STOCK USD.01",
      "ticker": "DHR",
      "identifier": "235851102",
      "pct_of_fund": 0.927601,
      "quantity": 1285.0,
      "market_value": 230194.9,
      "investments": "LT",
      "options_strike": 0.0,
      "sector": ""
    },
    {
      "name": "DEERE + CO COMMON STOCK USD1.0",
      "ticker": "DE",
      "identifier": "244199105",
      "pct_of_fund": 2.227058,
      "quantity": 910.0,
      "market_value": 552670.3,
      "investments": "LT",
      "options_strike": 0.0,
      "sector": ""
    },
    {
      "name": "NVIDIA CORP COMMON STOCK USD.001",
      "ticker": "NVDA",
      "identifier": "67066G104",
      "pct_of_fund": 5.575767,
      "quantity": 6525.0,
      "market_value": 1383691.5,
      "investments": "LT",
      "options_strike": 0.0,
      "sector": ""
    },
    {
      "name": "HUMANA INC COMMON STOCK USD.1666666",
      "ticker": "HUM",
      "identifier": "444859102",
      "pct_of_fund": 2.89354,
      "quantity": 1806.0,
      "market_value": 718065.6,
      "investments": "LT",
      "options_strike": 0.0,
      "sector": ""
    },
    {
      "name": "INTEL CORP COMMON STOCK USD.001",
      "ticker": "INTC",
      "identifier": "458140100",
      "pct_of_fund": 0.964744,
      "quantity": 2333.0,
      "market_value": 239412.46,
      "investments": "LT",
      "options_strike": 0.0,
      "sector": ""
    },
    {
      "name": "TELEDYNE TECHNOLOGIES INC COMMON STOCK USD.01",
      "ticker": "TDY",
      "identifier": "879360105",
      "pct_of_fund": 2.170416,
      "quantity": 828.0,
      "market_value": 538614.0,
      "investments": "LT",
      "options_strike": 0.0,
      "sector": ""
    },
    {
      "name": "MARSH + MCLENNAN COS COMMON STOCK USD1.0",
      "ticker": "MRSH",
      "identifier": "571748102",
      "pct_of_fund": 1.949838,
      "quantity": 2765.0,
      "market_value": 483875.0,
      "investments": "LT",
      "options_strike": 0.0,
      "sector": ""
    },
    {
      "name": "MICROSOFT CORP COMMON STOCK USD.00000625",
      "ticker": "MSFT",
      "identifier": "594918104",
      "pct_of_fund": 1.439228,
      "quantity": 915.0,
      "market_value": 357161.1,
      "investments": "LT",
      "options_strike": 0.0,
      "sector": ""
    },
    {
      "name": "MICRON TECHNOLOGY INC COMMON STOCK USD.1",
      "ticker": "MU",
      "identifier": "595112103",
      "pct_of_fund": 1.043915,
      "quantity": 270.0,
      "market_value": 259059.6,
      "investments": "LT",
      "options_strike": 0.0,
      "sector": ""
    },
    {
      "name": "CAPITAL ONE FINANCIAL CORP COMMON STOCK USD.01",
      "ticker": "COF",
      "identifier": "14040H105",
      "pct_of_fund": 2.643563,
      "quantity": 3258.0,
      "market_value": 656030.88,
      "investments": "LT",
      "options_strike": 0.0,
      "sector": ""
    },
    {
      "name": "OLD DOMINION FREIGHT LINE COMMON STOCK USD.1",
      "ticker": "ODFL",
      "identifier": "679580100",
      "pct_of_fund": 1.322718,
      "quantity": 1410.0,
      "market_value": 328248.0,
      "investments": "LT",
      "options_strike": 0.0,
      "sector": ""
    },
    {
      "name": "CONOCOPHILLIPS COMMON STOCK USD.01",
      "ticker": "COP",
      "identifier": "20825C104",
      "pct_of_fund": 1.930037,
      "quantity": 4032.0,
      "market_value": 478961.28,
      "investments": "LT",
      "options_strike": 0.0,
      "sector": ""
    },
    {
      "name": "COSTCO WHOLESALE CORP COMMON STOCK USD.005",
      "ticker": "COST",
      "identifier": "22160K105",
      "pct_of_fund": 1.079911,
      "quantity": 289.0,
      "market_value": 267992.59,
      "investments": "LT",
      "options_strike": 0.0,
      "sector": ""
    },
    {
      "name": "RENAISSANCERE HOLDINGS LTD COMMON STOCK USD1.0",
      "ticker": "RNR",
      "identifier": "G7496G103",
      "pct_of_fund": 1.655379,
      "quantity": 1285.0,
      "market_value": 410801.65,
      "investments": "LT",
      "options_strike": 0.0,
      "sector": ""
    },
    {
      "name": "SLB LTD COMMON STOCK USD.01",
      "ticker": "SLB",
      "identifier": "806857108",
      "pct_of_fund": 1.140261,
      "quantity": 5936.0,
      "market_value": 282969.12,
      "investments": "LT",
      "options_strike": 0.0,
      "sector": ""
    },
    {
      "name": "SONY GROUP CORP   SP ADR ADR",
      "ticker": "SONY",
      "identifier": "835699307",
      "pct_of_fund": 0.807171,
      "quantity": 9575.0,
      "market_value": 200309.0,
      "investments": "LT",
      "options_strike": 0.0,
      "sector": ""
    },
    {
      "name": "STEEL DYNAMICS INC COMMON STOCK USD.005",
      "ticker": "STLD",
      "identifier": "858119100",
      "pct_of_fund": 1.698241,
      "quantity": 1766.0,
      "market_value": 421438.24,
      "investments": "LT",
      "options_strike": 0.0,
      "sector": ""
    },
    {
      "name": "CME GROUP INC COMMON STOCK USD.01",
      "ticker": "CME",
      "identifier": "12572Q105",
      "pct_of_fund": 1.380975,
      "quantity": 1375.0,
      "market_value": 342705.0,
      "investments": "LT",
      "options_strike": 0.0,
      "sector": ""
    },
    {
      "name": "HANNOVER RUECK SE COMMON STOCK",
      "ticker": "HNR1",
      "identifier": "451180905",
      "pct_of_fund": 1.423751,
      "quantity": 1247.0,
      "market_value": 353320.33,
      "investments": "LT",
      "options_strike": 0.0,
      "sector": ""
    },
    {
      "name": "SCHNEIDER ELECTRIC SE COMMON STOCK EUR4.0",
      "ticker": "SU",
      "identifier": "483410007",
      "pct_of_fund": 1.308969,
      "quantity": 1064.0,
      "market_value": 324835.86,
      "investments": "LT",
      "options_strike": 0.0,
      "sector": ""
    },
    {
      "name": "BANK PEKAO SA COMMON STOCK PLN1.0",
      "ticker": "PEO",
      "identifier": "547311902",
      "pct_of_fund": 1.744385,
      "quantity": 6959.0,
      "market_value": 432889.41,
      "investments": "LT",
      "options_strike": 0.0,
      "sector": ""
    },
    {
      "name": "LENOVO GROUP LTD COMMON STOCK",
      "ticker": "992",
      "identifier": "621808906",
      "pct_of_fund": 0.475336,
      "quantity": 38000.0,
      "market_value": 117960.13,
      "investments": "LT",
      "options_strike": 0.0,
      "sector": ""
    },
    {
      "name": "SONY GROUP CORP COMMON STOCK",
      "ticker": "6758",
      "identifier": "682150008",
      "pct_of_fund": 0.811454,
      "quantity": 9600.0,
      "market_value": 201371.71,
      "investments": "LT",
      "options_strike": 0.0,
      "sector": ""
    },
    {
      "name": "FRANCO NEVADA CORP COMMON STOCK",
      "ticker": "FNV",
      "identifier": "351858105",
      "pct_of_fund": 2.01719,
      "quantity": 2338.0,
      "market_value": 500589.18,
      "investments": "LT",
      "options_strike": 0.0,
      "sector": ""
    },
    {
      "name": "MS+AD INSURANCE GROUP HOLDIN COMMON STOCK",
      "ticker": "8725",
      "identifier": "B2Q4CS905",
      "pct_of_fund": 0.944832,
      "quantity": 8000.0,
      "market_value": 234471.12,
      "investments": "LT",
      "options_strike": 0.0,
      "sector": ""
    },
    {
      "name": "O REILLY AUTOMOTIVE INC COMMON STOCK USD.01",
      "ticker": "ORLY",
      "identifier": "67103H107",
      "pct_of_fund": 1.583723,
      "quantity": 4542.0,
      "market_value": 393019.26,
      "investments": "LT",
      "options_strike": 0.0,
      "sector": ""
    },
    {
      "name": "META PLATFORMS INC CLASS A COMMON STOCK USD.000006",
      "ticker": "META",
      "identifier": "30303M102",
      "pct_of_fund": 1.700849,
      "quantity": 673.0,
      "market_value": 422085.41,
      "investments": "LT",
      "options_strike": 0.0,
      "sector": ""
    },
    {
      "name": "TECHNIPFMC PLC COMMON STOCK USD1.0",
      "ticker": "FTI",
      "identifier": "G87110105",
      "pct_of_fund": 1.161779,
      "quantity": 3839.0,
      "market_value": 288308.9,
      "investments": "LT",
      "options_strike": 0.0,
      "sector": ""
    },
    {
      "name": "BROADCOM INC COMMON STOCK",
      "ticker": "AVGO",
      "identifier": "11135F101",
      "pct_of_fund": 3.923941,
      "quantity": 2454.0,
      "market_value": 973771.74,
      "investments": "LT",
      "options_strike": 0.0,
      "sector": ""
    },
    {
      "name": "ARES MANAGEMENT CORP   A COMMON STOCK",
      "ticker": "ARES",
      "identifier": "03990B101",
      "pct_of_fund": 1.457996,
      "quantity": 3026.0,
      "market_value": 361818.82,
      "investments": "LT",
      "options_strike": 0.0,
      "sector": ""
    },
    {
      "name": "DELL TECHNOLOGIES  C COMMON STOCK",
      "ticker": "DELL",
      "identifier": "24703L202",
      "pct_of_fund": 1.504346,
      "quantity": 845.0,
      "market_value": 373321.0,
      "investments": "LT",
      "options_strike": 0.0,
      "sector": ""
    },
    {
      "name": "EQUINOX GOLD CORP COMMON STOCK",
      "ticker": "EQX",
      "identifier": "29446Y502",
      "pct_of_fund": 0.656862,
      "quantity": 17434.0,
      "market_value": 163007.9,
      "investments": "LT",
      "options_strike": 0.0,
      "sector": ""
    },
    {
      "name": "INGERSOLL RAND INC COMMON STOCK USD.01",
      "ticker": "IR",
      "identifier": "45687V106",
      "pct_of_fund": 1.769019,
      "quantity": 5255.0,
      "market_value": 439002.7,
      "investments": "LT",
      "options_strike": 0.0,
      "sector": ""
    },
    {
      "name": "ARISTA NETWORKS INC COMMON STOCK USD.0001",
      "ticker": "ANET",
      "identifier": "040413205",
      "pct_of_fund": 1.538276,
      "quantity": 2183.0,
      "market_value": 381741.21,
      "investments": "LT",
      "options_strike": 0.0,
      "sector": ""
    },
    {
      "name": "ATLAS COPCO AB A SHS COMMON STOCK SEK.16",
      "ticker": "ATCO A",
      "identifier": "BLDBN4902",
      "pct_of_fund": 1.603949,
      "quantity": 19194.0,
      "market_value": 398038.52,
      "investments": "LT",
      "options_strike": 0.0,
      "sector": ""
    },
    {
      "name": "SIEMENS ENERGY AG COMMON STOCK",
      "ticker": "ENR",
      "identifier": "ACI1RCRC2",
      "pct_of_fund": 1.257691,
      "quantity": 1811.0,
      "market_value": 312110.65,
      "investments": "LT",
      "options_strike": 0.0,
      "sector": ""
    },
    {
      "name": "APPLOVIN CORP CLASS A COMMON STOCK USD.00003",
      "ticker": "APP",
      "identifier": "03831W108",
      "pct_of_fund": 0.91584,
      "quantity": 551.0,
      "market_value": 227276.48,
      "investments": "LT",
      "options_strike": 0.0,
      "sector": ""
    },
    {
      "name": "APOLLO GLOBAL MANAGEMENT INC COMMON STOCK USD.0001",
      "ticker": "APO",
      "identifier": "03769M106",
      "pct_of_fund": 0.919561,
      "quantity": 1917.0,
      "market_value": 228199.68,
      "investments": "LT",
      "options_strike": 0.0,
      "sector": ""
    },
    {
      "name": "KOKUSAI ELECTRIC CORP COMMON STOCK",
      "ticker": "6525",
      "identifier": "BNGHNG905",
      "pct_of_fund": 1.126218,
      "quantity": 5200.0,
      "market_value": 279484.18,
      "investments": "LT",
      "options_strike": 0.0,
      "sector": ""
    },
    {
      "name": "LIBERTY MEDIA CORP FORMULA C TRACKING STK",
      "ticker": "FWONK",
      "identifier": "531229755",
      "pct_of_fund": 2.338808,
      "quantity": 5986.0,
      "market_value": 580402.56,
      "investments": "LT",
      "options_strike": 0.0,
      "sector": ""
    },
    {
      "name": "RECRUIT HOLDINGS CO LTD COMMON STOCK",
      "ticker": "6098",
      "identifier": "BQRRZ0906",
      "pct_of_fund": 1.57736,
      "quantity": 5200.0,
      "market_value": 391440.35,
      "investments": "LT",
      "options_strike": 0.0,
      "sector": ""
    },
    {
      "name": "UNICREDIT SPA COMMON STOCK",
      "ticker": "UCG",
      "identifier": "BYMXPS901",
      "pct_of_fund": 2.198322,
      "quantity": 5742.0,
      "market_value": 545539.13,
      "investments": "LT",
      "options_strike": 0.0,
      "sector": ""
    },
    {
      "name": "CARVANA CO COMMON STOCK USD.001",
      "ticker": "CVNA",
      "identifier": "146869102",
      "pct_of_fund": 0.715086,
      "quantity": 2828.0,
      "market_value": 177457.0,
      "investments": "LT",
      "options_strike": 0.0,
      "sector": ""
    },
    {
      "name": "ORSTED A/S COMMON STOCK DKK10.0",
      "ticker": "ORSTED",
      "identifier": "BYT16L900",
      "pct_of_fund": 1.395409,
      "quantity": 14836.0,
      "market_value": 346287.13,
      "investments": "LT",
      "options_strike": 0.0,
      "sector": ""
    },
    {
      "name": "SEA LTD ADR ADR USD.0005",
      "ticker": "SE",
      "identifier": "81141R100",
      "pct_of_fund": 2.126663,
      "quantity": 5032.0,
      "market_value": 527756.16,
      "investments": "LT",
      "options_strike": 0.0,
      "sector": ""
    },
    {
      "name": "ALPHABET INC CL C COMMON STOCK USD.001",
      "ticker": "GOOG",
      "identifier": "02079K107",
      "pct_of_fund": 3.640072,
      "quantity": 2642.0,
      "market_value": 903326.22,
      "investments": "LT",
      "options_strike": 0.0,
      "sector": ""
    },
    {
      "name": "FERRARI NV COMMON STOCK EUR.01",
      "ticker": "RACE",
      "identifier": "N3167Y103",
      "pct_of_fund": 1.62773,
      "quantity": 1087.0,
      "market_value": 403940.07,
      "investments": "LT",
      "options_strike": 0.0,
      "sector": ""
    },
    {
      "name": "Cash/Cash equivalent USD",
      "ticker": "",
      "identifier": "",
      "pct_of_fund": 3.631811,
      "quantity": 0.0,
      "market_value": 901276.21,
      "investments": "",
      "options_strike": 0.0,
      "sector": ""
    }
  ]
}